linenotipy/__init__.py
linenotipy/linenotipy.py
linenotipy-1.0.5.dist-info/LICENSE.txt
linenotipy-1.0.5.dist-info/METADATA
linenotipy-1.0.5.dist-info/WHEEL
linenotipy-1.0.5.dist-info/top_level.txt
linenotipy-1.0.5.dist-info/RECORD
