Metadata-Version: 2.1
Name: linenotipy
Version: 1.0.5
Summary: linenotipy is a python client library         for line notify api on Python 3.6 and above.
Home-page: https://github.com/10mohi6/line-notify-python
Author: 10mohi6
Author-email: 10.mohi.6.y@gmail.com
License: MIT
Keywords: line notify python
Platform: UNKNOWN
Classifier: Development Status :: 5 - Production/Stable
Classifier: Programming Language :: Python
Classifier: Programming Language :: Python :: 3
Classifier: Programming Language :: Python :: 3.6
Classifier: Programming Language :: Python :: 3.7
Classifier: Programming Language :: Python :: 3.8
Classifier: Programming Language :: Python :: 3.9
Classifier: Intended Audience :: Developers
Classifier: Topic :: Communications :: Chat
Classifier: Topic :: System :: Networking
Classifier: Topic :: Office/Business
Classifier: License :: OSI Approved :: MIT License
Requires-Python: >=3.6.0
License-File: LICENSE.txt
Requires-Dist: requests
